{
    "name": "RequiredPeople",
    "fields": [],
    "relationships": [
        {
            "relationshipType": "many-to-one",
            "otherEntityName": "normal",
            "otherEntityRelationshipName": "theRequiredPeople",
            "relationshipName": "theNormal",
            "otherEntityField": "id"
        }
    ],
    "changelogDate": "20190914033829",
    "entityTableName": "required_people",
    "dto": "no",
    "pagination": "no",
    "service": "no",
    "jpaMetamodelFiltering": false,
    "fluentMethods": true,
    "clientRootFolder": "",
    "applications": "*"
}